ipidea_proxy/__init__.py
ipidea_proxy/client.py
ipidea_proxy-0.7.0.dist-info/LICENSE
ipidea_proxy-0.7.0.dist-info/METADATA
ipidea_proxy-0.7.0.dist-info/WHEEL
ipidea_proxy-0.7.0.dist-info/top_level.txt
ipidea_proxy-0.7.0.dist-info/RECORD
