Metadata-Version: 2.1
Name: ipidea-proxy
Version: 0.7.0
Summary: Python Client for Ipidea Proxy Service API
Home-page: https://github.com/pinclr/ipidea-proxy
Author: Pinclr Coders
Author-email: Pinclr Coders <coding@pinclr.com>
Classifier: Programming Language :: Python :: 3
Classifier: License :: OSI Approved :: Apache Software License
Classifier: Operating System :: OS Independent
Requires-Python: >=3.6
License-File: LICENSE
